anyplusone/anyplusone.py
anyplusone-0.0.1.dist-info/METADATA
anyplusone-0.0.1.dist-info/WHEEL
anyplusone-0.0.1.dist-info/top_level.txt
anyplusone-0.0.1.dist-info/RECORD
