Metadata-Version: 2.1
Name: anyplusone
Version: 0.0.1
Summary: Simple math library
Home-page: https://github.com/<username>/anyplusone
Author: ay
Author-email: 
License: MIT
Platform: UNKNOWN
